MANIFEST.in
README.rst
requirements.txt
setup.py
cms/__init__.py
cms/cms.py
cms/code.py
cms/model.py
cms/util.py
cms/db/__init__.py
cms/db/mongodb.py
mongo_cms.egg-info/PKG-INFO
mongo_cms.egg-info/SOURCES.txt
mongo_cms.egg-info/dependency_links.txt
mongo_cms.egg-info/requires.txt
mongo_cms.egg-info/top_level.txt
scripts/cms