Metadata-Version: 1.0
Name: mongo-cms
Version: 0.0.5
Summary: UNKNOWN
Home-page: https://bitbucket.org/afriemann/cdn
Author: Aljosha Friemann
Author-email: aljosha.friemann@gmail.com
License: UNKNOWN
Platform: UNKNOWN
